{
  "title": "Network Spy",
  "description": "Analysing our SIEM we found this pcap, it seems that someone is spying us... But what have they stolen?\n\nAuthor: @slsanna\n\nsha1sum: `783b0f003074cb0df4401080245095ec330bd6a7`",
  "authors": [
    "slsanna"
  ],
  "tags": [
    "forensics"
  ],
  "hiddenTags": [],
  "flags": [
    "^srdnlen\\{S0r1gh3_pc4p\\}$"
  ],
  "scoring": {
    "type": "dynamic",
    "start": 50,
    "stop": 500,
    "decay": "30"
  },
  "files": [
    {
      "name": "mouse.pcap",
      "type": "upload",
      "path": "./attachments/mouse.pcap"
    }
  ],
  "hints": []
}